tests/__init__.py
truetool/__init__.py
truetool/command_line.py
truetool-3.0.3.dist-info/LICENSE
truetool-3.0.3.dist-info/METADATA
truetool-3.0.3.dist-info/WHEEL
truetool-3.0.3.dist-info/entry_points.txt
truetool-3.0.3.dist-info/top_level.txt
truetool-3.0.3.dist-info/RECORD
