Metadata-Version: 2.1
Name: truetool
Version: 3.0.3
Summary: An easy utility to managed frequently used TrueNAS SCALE CLI features
Home-page: https://github.com/truecharts/truetool
Author-email: into@truecharts.org
License: UNKNOWN
Platform: UNKNOWN
